{
  "document_id": "2-chr-23",
  "title": "2 Chronicles 23",
  "type": "study-bible",
  "translation": "NJPS",
  "blocks": [
    {
      "block_id": "jsb-2-chr-23-1",
      "type": "verse",
      "number": 1,
      "text": "In the seventh year, Jehoiada took courage and brought the chiefs of the hundreds, Azariah son of Jeroham, Ishmael son of Jehohanan, Azariah son of Obed, Maaseiah son of Adaiah, and Elishaphat son of Zichri, into a compact with him."
    },
    {
      "block_id": "jsb-2-chr-23-1-commentary-1",
      "type": "commentary",
      "text": "Cf. 2 Kings 11.4–20",
      "canonical_ref": {
        "work": "bible",
        "book": "2-chr",
        "chapter": 23,
        "verse": 1
      },
      "verse_start": 1,
      "verse_end": 1
    },
    {
      "block_id": "jsb-2-chr-23-2",
      "type": "verse",
      "number": 2,
      "text": "They went through Judah and assembled the Levites from all the towns of Judah, and the chiefs of the clans of Israel. They came to Jerusalem"
    },
    {
      "block_id": "jsb-2-chr-23-3",
      "type": "verse",
      "number": 3,
      "text": "and the entire assembly made a covenant with the king in the House of God. He said to them, “The son of the king shall be king according to the promise the Lord made concerning the sons of David."
    },
    {
      "block_id": "jsb-2-chr-23-3-commentary-2",
      "type": "commentary",
      "text": "I.e., Jehoiada.",
      "canonical_ref": {
        "work": "bible",
        "book": "2-chr",
        "chapter": 23,
        "verse": 3
      },
      "verse_start": 3,
      "verse_end": 3
    },
    {
      "block_id": "jsb-2-chr-23-4",
      "type": "verse",
      "number": 4,
      "text": "This is what you must do: One third of you, priests and Levites, who are on duty for the week, shall be gatekeepers at the thresholds;"
    },
    {
      "block_id": "jsb-2-chr-23-5",
      "type": "verse",
      "number": 5,
      "text": "another third shall be stationed in the royal palace, and the other third at the Foundation Gate. All the people shall be in the courts of the House of the Lord."
    },
    {
      "block_id": "jsb-2-chr-23-6",
      "type": "verse",
      "number": 6,
      "text": "Let no one enter the House of the Lord except the priests and the ministering Levites. They may enter because they are sanctified, but all the people shall obey the proscription of the Lord."
    },
    {
      "block_id": "jsb-2-chr-23-7",
      "type": "verse",
      "number": 7,
      "text": "The Levites shall surround the king on every side, every man with his weapons at the ready; and whoever enters the House shall be killed. Stay close to the king in his comings and goings.”"
    },
    {
      "block_id": "jsb-2-chr-23-8",
      "type": "verse",
      "number": 8,
      "text": "The Levites and all Judah did just as Jehoiada the priest ordered: each took his men—those who were on duty that week and those who were off duty that week, for Jehoiada the priest had not dismissed the divisions."
    },
    {
      "block_id": "jsb-2-chr-23-9",
      "type": "verse",
      "number": 9,
      "text": "Jehoiada the priest gave the chiefs of the hundreds King David’s spears and shields and quivers that were kept in the House of God."
    },
    {
      "block_id": "jsb-2-chr-23-10",
      "type": "verse",
      "number": 10,
      "text": "He stationed the entire force, each man with his weapons at the ready, from the south end of the House to the north end of the House, at the altar and the House, to guard the king on every side."
    },
    {
      "block_id": "jsb-2-chr-23-11",
      "type": "verse",
      "number": 11,
      "text": "Then they brought out the king’s son, and placed upon him the crown and the insignia. They proclaimed him king, and Jehoiada and his sons anointed him and shouted, “Long live the king!”"
    },
    {
      "block_id": "jsb-2-chr-23-12",
      "type": "verse",
      "number": 12,
      "text": "When Athaliah heard the shouting of the people and the guards and the acclamation of the king, she came out to the people, to the House of the Lord."
    },
    {
      "block_id": "jsb-2-chr-23-13",
      "type": "verse",
      "number": 13,
      "text": "She looked about and saw the king standing by his pillar at the entrance, the chiefs with their trumpets beside the king, and all the people of the land rejoicing and blowing trumpets, and the singers with musical instruments leading the hymns. Athaliah rent her garments and cried out, “Treason, treason!”"
    },
    {
      "block_id": "jsb-2-chr-23-14",
      "type": "verse",
      "number": 14,
      "text": "Then the priest Jehoiada ordered out the army officers, the chiefs of hundreds, and said to them, “Take her out between the ranks, and if anyone follows her, put him to the sword.” For the priest thought, “Let her not be put to death in the House of the Lord.”"
    },
    {
      "block_id": "jsb-2-chr-23-15",
      "type": "verse",
      "number": 15,
      "text": "They cleared a passage for her and she came to the entrance of the Horse Gate to the royal palace; there she was put to death."
    },
    {
      "block_id": "jsb-2-chr-23-16",
      "type": "verse",
      "number": 16,
      "text": "Then Jehoiada solemnized a covenant between himself and the people and the king that they should be the people of the Lord."
    },
    {
      "block_id": "jsb-2-chr-23-17",
      "type": "verse",
      "number": 17,
      "text": "All the people then went to the temple of Baal; they tore it down and smashed its altars and images to bits, and they slew Mattan, the priest of Baal, in front of the altars."
    },
    {
      "block_id": "jsb-2-chr-23-18",
      "type": "verse",
      "number": 18,
      "text": "Jehoiada put the officers of the House of the Lord in the charge of Levite priests whom David had assigned over the House of the Lord to offer up burnt offerings, as is prescribed in the Teaching of Moses, accompanied by joyful song as ordained by David."
    },
    {
      "block_id": "jsb-2-chr-23-19",
      "type": "verse",
      "number": 19,
      "text": "He stationed the gatekeepers at the gates of the House of the Lord to prevent the entry of anyone unclean for any reason."
    },
    {
      "block_id": "jsb-2-chr-23-20",
      "type": "verse",
      "number": 20,
      "text": "He took the chiefs of hundreds, the nobles, and the rulers of the people and all the people of the land, and they escorted the king down from the House of the Lord into the royal palace by the upper gate, and seated the king on the royal throne."
    },
    {
      "block_id": "jsb-2-chr-23-21",
      "type": "verse",
      "number": 21,
      "text": "All the people of the land rejoiced, and the city was quiet. As for Athaliah, she had been put to the sword."
    }
  ]
}