{
  "document_id": "isa-9",
  "title": "Isaiah 9",
  "type": "scripture",
  "translation": "NRSVue",
  "blocks": [
    {
      "block_id": "isa-9-heading-the-righteous-reign-",
      "type": "heading",
      "text": "The Righteous Reign of the Coming King"
    },
    {
      "block_id": "isa-9-1",
      "type": "verse",
      "number": 1,
      "text": "But there will be no gloom for those who were in anguish. In the former time he brought into contempt the land of Zebulun and the land of Naphtali, but in the latter time he will make glorious the way of the sea, the land beyond the Jordan, Galilee of the nations."
    },
    {
      "block_id": "isa-9-2",
      "type": "verse",
      "number": 2,
      "text": "The people who walked in darkness"
    },
    {
      "block_id": "isa-9-3",
      "type": "verse",
      "number": 3,
      "text": "You have multiplied exultation;"
    },
    {
      "block_id": "isa-9-4",
      "type": "verse",
      "number": 4,
      "text": "For the yoke of their burden"
    },
    {
      "block_id": "isa-9-5",
      "type": "verse",
      "number": 5,
      "text": "For all the boots of the tramping warriors"
    },
    {
      "block_id": "isa-9-6",
      "type": "verse",
      "number": 6,
      "text": "For a child has been born for us,"
    },
    {
      "block_id": "isa-9-7",
      "type": "verse",
      "number": 7,
      "text": "Great will be his authority,"
    },
    {
      "block_id": "isa-9-8",
      "type": "verse",
      "number": 8,
      "text": "The Lord sent a word against Jacob,"
    },
    {
      "block_id": "isa-9-9",
      "type": "verse",
      "number": 9,
      "text": "and all the people knew it—"
    },
    {
      "block_id": "isa-9-10",
      "type": "verse",
      "number": 10,
      "text": "“The bricks have fallen,"
    },
    {
      "block_id": "isa-9-11",
      "type": "verse",
      "number": 11,
      "text": "So the Lord raised adversaries against them"
    },
    {
      "block_id": "isa-9-12",
      "type": "verse",
      "number": 12,
      "text": "the Arameans on the east and the Philistines on the west,"
    },
    {
      "block_id": "isa-9-13",
      "type": "verse",
      "number": 13,
      "text": "The people did not turn to him who struck them"
    },
    {
      "block_id": "isa-9-14",
      "type": "verse",
      "number": 14,
      "text": "So the Lord cut off from Israel head and tail,"
    },
    {
      "block_id": "isa-9-15",
      "type": "verse",
      "number": 15,
      "text": "elders and dignitaries are the head,"
    },
    {
      "block_id": "isa-9-16",
      "type": "verse",
      "number": 16,
      "text": "for those who led this people led them astray,"
    },
    {
      "block_id": "isa-9-17",
      "type": "verse",
      "number": 17,
      "text": "That is why the Lord did not have pity on their young people"
    },
    {
      "block_id": "isa-9-18",
      "type": "verse",
      "number": 18,
      "text": "For wickedness burned like a fire,"
    },
    {
      "block_id": "isa-9-19",
      "type": "verse",
      "number": 19,
      "text": "Through the wrath of the Lord of hosts"
    },
    {
      "block_id": "isa-9-20",
      "type": "verse",
      "number": 20,
      "text": "They gorged on the right but still were hungry,"
    },
    {
      "block_id": "isa-9-21",
      "type": "verse",
      "number": 21,
      "text": "Manasseh devoured Ephraim, and Ephraim Manasseh,"
    }
  ]
}